{
	"$schema": "http://schema.management.azure.com/schemas/2015-01-01/deploymentTemplate.json#",
	"contentVersion": "1.0.0.0",
	"parameters": {
		"factoryName": {
			"type": "string",
			"metadata": "Data Factory name",
			"defaultValue": "SERDFDEV"
		}
	},
	"variables": {
		"factoryId": "[concat('Microsoft.DataFactory/factories/', parameters('factoryName'))]"
	},
	"resources": [
		{
			"name": "[concat(parameters('factoryName'), '/CD_SISBI_BI_Agencias')]",
			"type": "Microsoft.DataFactory/factories/pipelines",
			"apiVersion": "2018-06-01",
			"properties": {
				"activities": [
					{
						"name": "Copy_go0",
						"type": "Copy",
						"dependsOn": [],
						"policy": {
							"timeout": "7.00:00:00",
							"retry": 0,
							"retryIntervalInSeconds": 30,
							"secureOutput": false,
							"secureInput": false
						},
						"userProperties": [
							{
								"name": "Source",
								"value": "dbo.BI_Agencias"
							},
							{
								"name": "Destination",
								"value": "SISBI/BI_Agencias"
							}
						],
						"typeProperties": {
							"source": {
								"type": "SqlServerSource"
							},
							"sink": {
								"type": "ParquetSink",
								"storeSettings": {
									"type": "AzureBlobFSWriteSettings"
								}
							},
							"enableStaging": false
						},
						"inputs": [
							{
								"referenceName": "SourceDataset_BI_Agencias",
								"type": "DatasetReference",
								"parameters": {}
							}
						],
						"outputs": [
							{
								"referenceName": "Destination_BI_Agencias",
								"type": "DatasetReference",
								"parameters": {}
							}
						]
					}
				],
				"annotations": []
			},
			"dependsOn": []
		},
		{
			"name": "[concat(parameters('factoryName'), '/CD_SISBI_BI_AmbitoActividadEcononica')]",
			"type": "Microsoft.DataFactory/factories/pipelines",
			"apiVersion": "2018-06-01",
			"properties": {
				"activities": [
					{
						"name": "Copy_z5k",
						"type": "Copy",
						"dependsOn": [],
						"policy": {
							"timeout": "7.00:00:00",
							"retry": 0,
							"retryIntervalInSeconds": 30,
							"secureOutput": false,
							"secureInput": false
						},
						"userProperties": [
							{
								"name": "Source",
								"value": "dbo.BI_AmbitoActividadEcononica"
							},
							{
								"name": "Destination",
								"value": "SISBI/BI_AmbitoActividadEcononica"
							}
						],
						"typeProperties": {
							"source": {
								"type": "SqlServerSource"
							},
							"sink": {
								"type": "ParquetSink",
								"storeSettings": {
									"type": "AzureDataLakeStoreWriteSettings"
								}
							},
							"enableStaging": false
						},
						"inputs": [
							{
								"referenceName": "SourceDataset_BI_AmbitoActividadEcononica",
								"type": "DatasetReference",
								"parameters": {}
							}
						],
						"outputs": [
							{
								"referenceName": "DestinationDataset_BI_AmbitoActividadEcononica",
								"type": "DatasetReference",
								"parameters": {}
							}
						]
					}
				],
				"annotations": []
			},
			"dependsOn": []
		},
		{
			"name": "[concat(parameters('factoryName'), '/CD_SISBI_BI_BIDerechos')]",
			"type": "Microsoft.DataFactory/factories/pipelines",
			"apiVersion": "2018-06-01",
			"properties": {
				"activities": [
					{
						"name": "Copy_4fc",
						"type": "Copy",
						"dependsOn": [],
						"policy": {
							"timeout": "7.00:00:00",
							"retry": 0,
							"retryIntervalInSeconds": 30,
							"secureOutput": false,
							"secureInput": false
						},
						"userProperties": [
							{
								"name": "Source",
								"value": "dbo.BI_BIDerechos"
							},
							{
								"name": "Destination",
								"value": "SISBI/BI_BIDerechos"
							}
						],
						"typeProperties": {
							"source": {
								"type": "SqlServerSource"
							},
							"sink": {
								"type": "ParquetSink",
								"storeSettings": {
									"type": "AzureDataLakeStoreWriteSettings"
								}
							},
							"enableStaging": false
						},
						"inputs": [
							{
								"referenceName": "SourceDataset_4fc",
								"type": "DatasetReference",
								"parameters": {}
							}
						],
						"outputs": [
							{
								"referenceName": "DestinationDataset_4fc",
								"type": "DatasetReference",
								"parameters": {}
							}
						]
					}
				],
				"annotations": []
			},
			"dependsOn": []
		},
		{
			"name": "[concat(parameters('factoryName'), '/CD_SISBI_BI_BMBienesM')]",
			"type": "Microsoft.DataFactory/factories/pipelines",
			"apiVersion": "2018-06-01",
			"properties": {
				"activities": [
					{
						"name": "Copy_kyo",
						"type": "Copy",
						"dependsOn": [],
						"policy": {
							"timeout": "7.00:00:00",
							"retry": 0,
							"retryIntervalInSeconds": 30,
							"secureOutput": false,
							"secureInput": false
						},
						"userProperties": [
							{
								"name": "Source",
								"value": "dbo.BI_BMBienesM"
							},
							{
								"name": "Destination",
								"value": "SISBI/BI_BMBienesM"
							}
						],
						"typeProperties": {
							"source": {
								"type": "SqlServerSource"
							},
							"sink": {
								"type": "ParquetSink",
								"storeSettings": {
									"type": "AzureDataLakeStoreWriteSettings"
								}
							},
							"enableStaging": false
						},
						"inputs": [
							{
								"referenceName": "SourceDataset_BI_BMBienesM",
								"type": "DatasetReference",
								"parameters": {}
							}
						],
						"outputs": [
							{
								"referenceName": "DestinationDataset_BI_BMBienesM",
								"type": "DatasetReference",
								"parameters": {}
							}
						]
					}
				],
				"annotations": []
			},
			"dependsOn": []
		},
		{
			"name": "[concat(parameters('factoryName'), '/CD_SISBI_BI_BMCodigosEspecifica')]",
			"type": "Microsoft.DataFactory/factories/pipelines",
			"apiVersion": "2018-06-01",
			"properties": {
				"activities": [
					{
						"name": "Copy_bor",
						"type": "Copy",
						"dependsOn": [],
						"policy": {
							"timeout": "7.00:00:00",
							"retry": 0,
							"retryIntervalInSeconds": 30,
							"secureOutput": false,
							"secureInput": false
						},
						"userProperties": [
							{
								"name": "Source",
								"value": "dbo.BI_BMCodigosEspecifica"
							},
							{
								"name": "Destination",
								"value": "SISBI/BI_BMCodigosEspecifica"
							}
						],
						"typeProperties": {
							"source": {
								"type": "SqlServerSource"
							},
							"sink": {
								"type": "ParquetSink",
								"storeSettings": {
									"type": "AzureDataLakeStoreWriteSettings"
								}
							},
							"enableStaging": false
						},
						"inputs": [
							{
								"referenceName": "SourceDataset_BI_BMCodigosEspecifica",
								"type": "DatasetReference",
								"parameters": {}
							}
						],
						"outputs": [
							{
								"referenceName": "DestinationDataset_BI_BMCodigosEspecifica",
								"type": "DatasetReference",
								"parameters": {}
							}
						]
					}
				],
				"annotations": []
			},
			"dependsOn": []
		},
		{
			"name": "[concat(parameters('factoryName'), '/CD_SISBI_BI_BMDerechos')]",
			"type": "Microsoft.DataFactory/factories/pipelines",
			"apiVersion": "2018-06-01",
			"properties": {
				"activities": [
					{
						"name": "Copy_qsk",
						"type": "Copy",
						"dependsOn": [],
						"policy": {
							"timeout": "7.00:00:00",
							"retry": 0,
							"retryIntervalInSeconds": 30,
							"secureOutput": false,
							"secureInput": false
						},
						"userProperties": [
							{
								"name": "Source",
								"value": "dbo.BI_BMDerechos"
							},
							{
								"name": "Destination",
								"value": "SISBI/BI_BMDerechos"
							}
						],
						"typeProperties": {
							"source": {
								"type": "SqlServerSource"
							},
							"sink": {
								"type": "ParquetSink",
								"storeSettings": {
									"type": "AzureDataLakeStoreWriteSettings"
								}
							},
							"enableStaging": false
						},
						"inputs": [
							{
								"referenceName": "SourceDataset_BI_BMDerechos",
								"type": "DatasetReference",
								"parameters": {}
							}
						],
						"outputs": [
							{
								"referenceName": "DestinationDataset_BI_BMDerechos",
								"type": "DatasetReference",
								"parameters": {}
							}
						]
					}
				],
				"annotations": []
			},
			"dependsOn": []
		},
		{
			"name": "[concat(parameters('factoryName'), '/CD_SISBI_BI_BMPrestaciones')]",
			"type": "Microsoft.DataFactory/factories/pipelines",
			"apiVersion": "2018-06-01",
			"properties": {
				"activities": [
					{
						"name": "Copy_96k",
						"type": "Copy",
						"dependsOn": [],
						"policy": {
							"timeout": "7.00:00:00",
							"retry": 0,
							"retryIntervalInSeconds": 30,
							"secureOutput": false,
							"secureInput": false
						},
						"userProperties": [
							{
								"name": "Source",
								"value": "dbo.BI_BMPrestaciones"
							},
							{
								"name": "Destination",
								"value": "SISBI/BI_BMPrestaciones"
							}
						],
						"typeProperties": {
							"source": {
								"type": "SqlServerSource"
							},
							"sink": {
								"type": "ParquetSink",
								"storeSettings": {
									"type": "AzureDataLakeStoreWriteSettings"
								}
							},
							"enableStaging": false
						},
						"inputs": [
							{
								"referenceName": "SourceDataset_96k",
								"type": "DatasetReference",
								"parameters": {}
							}
						],
						"outputs": [
							{
								"referenceName": "DestinationDataset_96k",
								"type": "DatasetReference",
								"parameters": {}
							}
						]
					}
				],
				"annotations": []
			},
			"dependsOn": []
		},
		{
			"name": "[concat(parameters('factoryName'), '/CD_SISBI_BI_BMVehiculos')]",
			"type": "Microsoft.DataFactory/factories/pipelines",
			"apiVersion": "2018-06-01",
			"properties": {
				"activities": [
					{
						"name": "Copy_q1d",
						"type": "Copy",
						"dependsOn": [],
						"policy": {
							"timeout": "7.00:00:00",
							"retry": 0,
							"retryIntervalInSeconds": 30,
							"secureOutput": false,
							"secureInput": false
						},
						"userProperties": [
							{
								"name": "Source",
								"value": "dbo.BI_BMVehiculos"
							},
							{
								"name": "Destination",
								"value": "SISBI/BI_BMVehiculos"
							}
						],
						"typeProperties": {
							"source": {
								"type": "SqlServerSource"
							},
							"sink": {
								"type": "ParquetSink",
								"storeSettings": {
									"type": "AzureDataLakeStoreWriteSettings"
								}
							},
							"enableStaging": false
						},
						"inputs": [
							{
								"referenceName": "SourceDataset_BI_BMVehiculos",
								"type": "DatasetReference",
								"parameters": {}
							}
						],
						"outputs": [
							{
								"referenceName": "DestinationDataset_BI_BMVehiculos",
								"type": "DatasetReference",
								"parameters": {}
							}
						]
					}
				],
				"annotations": []
			},
			"dependsOn": []
		},
		{
			"name": "[concat(parameters('factoryName'), '/CD_SISBI_BI_Bancas')]",
			"type": "Microsoft.DataFactory/factories/pipelines",
			"apiVersion": "2018-06-01",
			"properties": {
				"activities": [
					{
						"name": "Copy_mfh",
						"type": "Copy",
						"dependsOn": [],
						"policy": {
							"timeout": "7.00:00:00",
							"retry": 0,
							"retryIntervalInSeconds": 30,
							"secureOutput": false,
							"secureInput": false
						},
						"userProperties": [
							{
								"name": "Source",
								"value": "dbo.BI_Bancas"
							},
							{
								"name": "Destination",
								"value": "SISBI/BI_Bancas"
							}
						],
						"typeProperties": {
							"source": {
								"type": "SqlServerSource"
							},
							"sink": {
								"type": "ParquetSink",
								"storeSettings": {
									"type": "AzureBlobFSWriteSettings"
								}
							},
							"enableStaging": false
						},
						"inputs": [
							{
								"referenceName": "SourceDataset_BI_Bancas",
								"type": "DatasetReference",
								"parameters": {}
							}
						],
						"outputs": [
							{
								"referenceName": "Destination_BI_Bancas",
								"type": "DatasetReference",
								"parameters": {}
							}
						]
					}
				],
				"annotations": []
			},
			"dependsOn": []
		},
		{
			"name": "[concat(parameters('factoryName'), '/CD_SISBI_BI_BeneficiariosCaptacion')]",
			"type": "Microsoft.DataFactory/factories/pipelines",
			"apiVersion": "2018-06-01",
			"properties": {
				"activities": [
					{
						"name": "Copy_2sg",
						"type": "Copy",
						"dependsOn": [],
						"policy": {
							"timeout": "7.00:00:00",
							"retry": 0,
							"retryIntervalInSeconds": 30,
							"secureOutput": false,
							"secureInput": false
						},
						"userProperties": [
							{
								"name": "Source",
								"value": "dbo.BI_BeneficiariosCaptacion"
							},
							{
								"name": "Destination",
								"value": "SISBI/BI_BeneficiariosCaptacion"
							}
						],
						"typeProperties": {
							"source": {
								"type": "SqlServerSource"
							},
							"sink": {
								"type": "ParquetSink",
								"storeSettings": {
									"type": "AzureDataLakeStoreWriteSettings"
								}
							},
							"enableStaging": false
						},
						"inputs": [
							{
								"referenceName": "SourceDataset_BI_BeneficiariosCaptacion",
								"type": "DatasetReference",
								"parameters": {}
							}
						],
						"outputs": [
							{
								"referenceName": "DestinationDataset_BI_BeneficiariosCaptacion",
								"type": "DatasetReference",
								"parameters": {}
							}
						]
					}
				],
				"annotations": []
			},
			"dependsOn": []
		},
		{
			"name": "[concat(parameters('factoryName'), '/CD_SISBI_BI_CICDeudores')]",
			"type": "Microsoft.DataFactory/factories/pipelines",
			"apiVersion": "2018-06-01",
			"properties": {
				"activities": [
					{
						"name": "Copy_pny",
						"type": "Copy",
						"dependsOn": [],
						"policy": {
							"timeout": "7.00:00:00",
							"retry": 0,
							"retryIntervalInSeconds": 30,
							"secureOutput": false,
							"secureInput": false
						},
						"userProperties": [
							{
								"name": "Source",
								"value": "dbo.BI_CICDeudores"
							},
							{
								"name": "Destination",
								"value": "SISBI/BI_CICDeudores"
							}
						],
						"typeProperties": {
							"source": {
								"type": "SqlServerSource"
							},
							"sink": {
								"type": "ParquetSink",
								"storeSettings": {
									"type": "AzureDataLakeStoreWriteSettings"
								}
							},
							"enableStaging": false
						},
						"inputs": [
							{
								"referenceName": "SourceDataset_BI_CICDeudores",
								"type": "DatasetReference",
								"parameters": {}
							}
						],
						"outputs": [
							{
								"referenceName": "DestinationDataset_BI_CICDeudores",
								"type": "DatasetReference",
								"parameters": {}
							}
						]
					}
				],
				"annotations": []
			},
			"dependsOn": []
		},
		{
			"name": "[concat(parameters('factoryName'), '/CD_SISBI_BI_CaptaCuotas')]",
			"type": "Microsoft.DataFactory/factories/pipelines",
			"apiVersion": "2018-06-01",
			"properties": {
				"activities": [
					{
						"name": "Copy_9lq",
						"type": "Copy",
						"dependsOn": [],
						"policy": {
							"timeout": "7.00:00:00",
							"retry": 0,
							"retryIntervalInSeconds": 30,
							"secureOutput": false,
							"secureInput": false
						},
						"userProperties": [
							{
								"name": "Source",
								"value": "dbo.BI_CaptaCuotas"
							},
							{
								"name": "Destination",
								"value": "SISBI/BI_CaptaCuotas"
							}
						],
						"typeProperties": {
							"source": {
								"type": "SqlServerSource"
							},
							"sink": {
								"type": "ParquetSink",
								"storeSettings": {
									"type": "AzureDataLakeStoreWriteSettings"
								}
							},
							"enableStaging": false
						},
						"inputs": [
							{
								"referenceName": "SourceDataset_BI_CaptaCuotas",
								"type": "DatasetReference",
								"parameters": {}
							}
						],
						"outputs": [
							{
								"referenceName": "DestinationDataset_BI_CaptaCuotas",
								"type": "DatasetReference",
								"parameters": {}
							}
						]
					}
				],
				"annotations": []
			},
			"dependsOn": []
		},
		{
			"name": "[concat(parameters('factoryName'), '/CD_SISBI_BI_CarteraPriorizada')]",
			"type": "Microsoft.DataFactory/factories/pipelines",
			"apiVersion": "2018-06-01",
			"properties": {
				"activities": [
					{
						"name": "Copy_zhp",
						"type": "Copy",
						"dependsOn": [],
						"policy": {
							"timeout": "7.00:00:00",
							"retry": 0,
							"retryIntervalInSeconds": 30,
							"secureOutput": false,
							"secureInput": false
						},
						"userProperties": [
							{
								"name": "Source",
								"value": "dbo.BI_CarteraPriorizada"
							},
							{
								"name": "Destination",
								"value": "SISBI/BI_CarteraPriorizada"
							}
						],
						"typeProperties": {
							"source": {
								"type": "SqlServerSource"
							},
							"sink": {
								"type": "ParquetSink",
								"storeSettings": {
									"type": "AzureDataLakeStoreWriteSettings"
								}
							},
							"enableStaging": false
						},
						"inputs": [
							{
								"referenceName": "SourceDataset_BI_CarteraPriorizada",
								"type": "DatasetReference",
								"parameters": {}
							}
						],
						"outputs": [
							{
								"referenceName": "Destination_BI_CarteraPriorizada",
								"type": "DatasetReference",
								"parameters": {}
							}
						]
					}
				],
				"annotations": []
			},
			"dependsOn": []
		},
		{
			"name": "[concat(parameters('factoryName'), '/CD_SISBI_BI_CatPostRestrict')]",
			"type": "Microsoft.DataFactory/factories/pipelines",
			"apiVersion": "2018-06-01",
			"properties": {
				"activities": [
					{
						"name": "Copy_cy5",
						"type": "Copy",
						"dependsOn": [],
						"policy": {
							"timeout": "7.00:00:00",
							"retry": 0,
							"retryIntervalInSeconds": 30,
							"secureOutput": false,
							"secureInput": false
						},
						"userProperties": [
							{
								"name": "Source",
								"value": "dbo.BI_CatPostRestrict"
							},
							{
								"name": "Destination",
								"value": "SISBI/BI_CatPostRestrict"
							}
						],
						"typeProperties": {
							"source": {
								"type": "SqlServerSource"
							},
							"sink": {
								"type": "ParquetSink",
								"storeSettings": {
									"type": "AzureBlobFSWriteSettings"
								}
							},
							"enableStaging": false
						},
						"inputs": [
							{
								"referenceName": "SourceDataset_BI_CatPostRestrict",
								"type": "DatasetReference",
								"parameters": {}
							}
						],
						"outputs": [
							{
								"referenceName": "DestinationDataset_BI_CatPostRestrict",
								"type": "DatasetReference",
								"parameters": {}
							}
						]
					}
				],
				"annotations": []
			},
			"dependsOn": []
		},
		{
			"name": "[concat(parameters('factoryName'), '/CD_SISBI_BI_CategoriaRiesgo')]",
			"type": "Microsoft.DataFactory/factories/pipelines",
			"apiVersion": "2018-06-01",
			"properties": {
				"activities": [
					{
						"name": "Copy_7xr",
						"type": "Copy",
						"dependsOn": [],
						"policy": {
							"timeout": "7.00:00:00",
							"retry": 0,
							"retryIntervalInSeconds": 30,
							"secureOutput": false,
							"secureInput": false
						},
						"userProperties": [
							{
								"name": "Source",
								"value": "dbo.BI_CategoriaRiesgo"
							},
							{
								"name": "Destination",
								"value": "SISBI/BI_CategoriaRiesgo"
							}
						],
						"typeProperties": {
							"source": {
								"type": "SqlServerSource"
							},
							"sink": {
								"type": "ParquetSink",
								"storeSettings": {
									"type": "AzureDataLakeStoreWriteSettings"
								}
							},
							"enableStaging": false
						},
						"inputs": [
							{
								"referenceName": "SourceDataset_BI_CategoriaRiesgo",
								"type": "DatasetReference",
								"parameters": {}
							}
						],
						"outputs": [
							{
								"referenceName": "Destination_BI_CategoriaRiesgo",
								"type": "DatasetReference",
								"parameters": {}
							}
						]
					}
				],
				"annotations": []
			},
			"dependsOn": []
		},
		{
			"name": "[concat(parameters('factoryName'), '/CD_SISBI_BI_CategoriasProd')]",
			"type": "Microsoft.DataFactory/factories/pipelines",
			"apiVersion": "2018-06-01",
			"properties": {
				"activities": [
					{
						"name": "Copy_exj",
						"type": "Copy",
						"dependsOn": [],
						"policy": {
							"timeout": "7.00:00:00",
							"retry": 0,
							"retryIntervalInSeconds": 30,
							"secureOutput": false,
							"secureInput": false
						},
						"userProperties": [
							{
								"name": "Source",
								"value": "dbo.BI_CategoriasProd"
							},
							{
								"name": "Destination",
								"value": "SISBI/BI_CategoriasProd"
							}
						],
						"typeProperties": {
							"source": {
								"type": "SqlServerSource"
							},
							"sink": {
								"type": "ParquetSink",
								"storeSettings": {
									"type": "AzureDataLakeStoreWriteSettings"
								}
							},
							"enableStaging": false
						},
						"inputs": [
							{
								"referenceName": "SourceDataset_BI_CategoriasProd",
								"type": "DatasetReference",
								"parameters": {}
							}
						],
						"outputs": [
							{
								"referenceName": "DestinationDataset_BI_CategoriasProd",
								"type": "DatasetReference",
								"parameters": {}
							}
						]
					}
				],
				"annotations": []
			},
			"dependsOn": []
		},
		{
			"name": "[concat(parameters('factoryName'), '/CD_SISBI_BI_CkCupones')]",
			"type": "Microsoft.DataFactory/factories/pipelines",
			"apiVersion": "2018-06-01",
			"properties": {
				"activities": [
					{
						"name": "Copy_ja4",
						"type": "Copy",
						"dependsOn": [],
						"policy": {
							"timeout": "7.00:00:00",
							"retry": 0,
							"retryIntervalInSeconds": 30,
							"secureOutput": false,
							"secureInput": false
						},
						"userProperties": [
							{
								"name": "Source",
								"value": "dbo.BI_CkCupones"
							},
							{
								"name": "Destination",
								"value": "SISBI/BI_CkCupones"
							}
						],
						"typeProperties": {
							"source": {
								"type": "SqlServerSource"
							},
							"sink": {
								"type": "ParquetSink",
								"storeSettings": {
									"type": "AzureDataLakeStoreWriteSettings"
								}
							},
							"enableStaging": false
						},
						"inputs": [
							{
								"referenceName": "SourceDataset_BI_CkCupones",
								"type": "DatasetReference",
								"parameters": {}
							}
						],
						"outputs": [
							{
								"referenceName": "DestinationDataset_BI_CkCupones",
								"type": "DatasetReference",
								"parameters": {}
							}
						]
					}
				],
				"annotations": []
			},
			"dependsOn": []
		},
		{
			"name": "[concat(parameters('factoryName'), '/CD_SISBI_BI_CliExcluidos')]",
			"type": "Microsoft.DataFactory/factories/pipelines",
			"apiVersion": "2018-06-01",
			"properties": {
				"activities": [
					{
						"name": "Copy_ogw",
						"type": "Copy",
						"dependsOn": [],
						"policy": {
							"timeout": "7.00:00:00",
							"retry": 0,
							"retryIntervalInSeconds": 30,
							"secureOutput": false,
							"secureInput": false
						},
						"userProperties": [
							{
								"name": "Source",
								"value": "dbo.BI_CliExcluidos"
							},
							{
								"name": "Destination",
								"value": "SISBI/BI_CliExcluidos"
							}
						],
						"typeProperties": {
							"source": {
								"type": "SqlServerSource"
							},
							"sink": {
								"type": "ParquetSink",
								"storeSettings": {
									"type": "AzureDataLakeStoreWriteSettings"
								}
							},
							"enableStaging": false
						},
						"inputs": [
							{
								"referenceName": "SourceDataset_BI_CliExcluidos",
								"type": "DatasetReference",
								"parameters": {}
							}
						],
						"outputs": [
							{
								"referenceName": "DestinationDataset_BI_CliExcluidos",
								"type": "DatasetReference",
								"parameters": {}
							}
						]
					}
				],
				"annotations": []
			},
			"dependsOn": []
		},
		{
			"name": "[concat(parameters('factoryName'), '/CD_SISBI_BI_ClientCorpo')]",
			"type": "Microsoft.DataFactory/factories/pipelines",
			"apiVersion": "2018-06-01",
			"properties": {
				"activities": [
					{
						"name": "Copy_s2n",
						"type": "Copy",
						"dependsOn": [],
						"policy": {
							"timeout": "7.00:00:00",
							"retry": 0,
							"retryIntervalInSeconds": 30,
							"secureOutput": false,
							"secureInput": false
						},
						"userProperties": [
							{
								"name": "Source",
								"value": "dbo.BI_ClientCorpo"
							},
							{
								"name": "Destination",
								"value": "SISBI/BI_ClientCorpo"
							}
						],
						"typeProperties": {
							"source": {
								"type": "SqlServerSource"
							},
							"sink": {
								"type": "ParquetSink",
								"storeSettings": {
									"type": "AzureDataLakeStoreWriteSettings"
								}
							},
							"enableStaging": false
						},
						"inputs": [
							{
								"referenceName": "SourceDataset_BI_ClientCorpo",
								"type": "DatasetReference",
								"parameters": {}
							}
						],
						"outputs": [
							{
								"referenceName": "Destination_BI_ClientCorpo",
								"type": "DatasetReference",
								"parameters": {}
							}
						]
					}
				],
				"annotations": []
			},
			"dependsOn": []
		},
		{
			"name": "[concat(parameters('factoryName'), '/CD_SISBI_BI_ClientHisto')]",
			"type": "Microsoft.DataFactory/factories/pipelines",
			"apiVersion": "2018-06-01",
			"properties": {
				"activities": [
					{
						"name": "Copy_bqr",
						"type": "Copy",
						"dependsOn": [],
						"policy": {
							"timeout": "7.00:00:00",
							"retry": 0,
							"retryIntervalInSeconds": 30,
							"secureOutput": false,
							"secureInput": false
						},
						"userProperties": [
							{
								"name": "Source",
								"value": "dbo.BI_ClientHisto"
							},
							{
								"name": "Destination",
								"value": "SISBI/BI_ClientHisto"
							}
						],
						"typeProperties": {
							"source": {
								"type": "SqlServerSource"
							},
							"sink": {
								"type": "ParquetSink",
								"storeSettings": {
									"type": "AzureDataLakeStoreWriteSettings"
								}
							},
							"enableStaging": false
						},
						"inputs": [
							{
								"referenceName": "SourceDataset_bqr",
								"type": "DatasetReference",
								"parameters": {}
							}
						],
						"outputs": [
							{
								"referenceName": "DestinationDataset_bqr",
								"type": "DatasetReference",
								"parameters": {}
							}
						]
					}
				],
				"annotations": []
			},
			"dependsOn": []
		}
	]
}